[
  {
    "slug": "electronics",
    "name": "Electronics",
    "img": "https://imgur.com/RKcQgdY.png"
  },
  {
    "slug": "fashion",
    "name": "Fashion",
    "img": "https://imgur.com/nr9VzIl.png"
  },
  {
    "slug": "home-kitchen",
    "name": "Home & Kitchen",
    "img": "https://imgur.com/14JdjC4.png"
  },
  {
    "slug": "BeautyCare",
    "name": "Beauty & Care",
    "img": "https://imgur.com/f3xUf7E.png"
  },

  {
    "slug": "toys-games",
    "name": "Toys & Games",
    "img": "https://imgur.com/0aYFGuW.png"
  },
  {
    "slug": "books",
    "name": "Books",
    "img": "https://imgur.com/6IZPZFd.png"
  },

  
  {
    "slug": "groceries",
    "name": "Groceries",
    "img": "https://imgur.com/I4Hxtxp.png"
  },
 
  {
    "slug": "jewelry",
    "name": "Jewelry",
    "img": "https://imgur.com/XZuDh32.png"
  },
  {
    "slug": "furniture",
    "name": "Furniture",
    "img": "https://imgur.com/34ydRhf.png"
  },
  
  {
    "slug": "smartphones",
    "name": "Smartphones",
    "img": "https://imgur.com/0Fir3hY.png"
  },
  {
    "slug": "watches",
    "name": "Watches",
    "img": "https://imgur.com/9DxDY5x.png"
  },
  

  {
    "slug": "baby-products",
    "name": "Baby Products",
    "img": "https://imgur.com/5b6ZUBF.png"
  }
]
